appoint_logger/__init__.py
appoint_logger/main.py
appoint_logger-2.0.3.dist-info/METADATA
appoint_logger-2.0.3.dist-info/WHEEL
appoint_logger-2.0.3.dist-info/top_level.txt
appoint_logger-2.0.3.dist-info/RECORD
