Metadata-Version: 2.1
Name: appoint-logger
Version: 2.0.3
Summary: A logger package for Appoint applications
Home-page: https://github.com/appointit-io/logger
Author: Guy Shaked
Author-email: dev.shakedguy@gmail.com
Classifier: Programming Language :: Python :: 3
Classifier: License :: OSI Approved :: MIT License
Classifier: Operating System :: OS Independent
Requires-Python: >=3.10
Requires-Dist: httpx>=0.27.2
Requires-Dist: colorama>=0.4.4
Provides-Extra: dev
Requires-Dist: ruff>=0.7.4; extra == "dev"
Requires-Dist: pytest>=8.3.3; extra == "dev"
Requires-Dist: pre-commit>=4.0.1; extra == "dev"
Requires-Dist: coverage>=7.6.7; extra == "dev"
